datret/__init__.py
datret/datret.py
datret-1.0.0.dist-info/LICENSE
datret-1.0.0.dist-info/METADATA
datret-1.0.0.dist-info/WHEEL
datret-1.0.0.dist-info/top_level.txt
datret-1.0.0.dist-info/RECORD
