Metadata-Version: 2.1
Name: datret
Version: 1.0.0
Summary: Tensorflow implementation for structured tabular data
Home-page: https://github.com/AbdualimovTP/datret
Author: Timur Abdualimov
Author-email: timur.atp@yandex.ru
License: UNKNOWN
Platform: UNKNOWN
Classifier: Programming Language :: Python :: 3.7
Classifier: License :: OSI Approved :: MIT License
License-File: LICENSE
